{"cameraMode":{"drawMode":0,"name":"Shaded","section":"Shading Mode"},"sceneLighting":true,"audioPlay":false,"sceneViewState":{"showFog":true,"showMaterialUpdate":false,"showSkybox":true,"showFlares":true,"showImageEffects":true,"showParticleSystems":true},"in2DMode":false,"pivot":{"x":3.0310487747192385,"y":0.16887998580932618,"z":5.655235290527344},"rotation":{"x":0.1600286215543747,"y":0.506092369556427,"z":-0.0961817055940628,"w":0.842035710811615},"size":20.41838264465332,"orthographic":false}